<?xml version="1.0" encoding="UTF-8" standalone="yes"?><blockSummary><originalFile>org/eclipse/jdt/internal/compiler/lookup/AnnotationHolder.java</originalFile><modifiedFile>org/eclipse/jdt/internal/compiler/lookup/AnnotationHolder.java</modifiedFile><classSummary><className>org.eclipse.jdt.internal.compiler.lookup.AnnotationHolder</className><computeMetaData>heuristics</computeMetaData><methodSummary><methodName>AnnotationHolder</methodName><modMethodReturnType>void</modMethodReturnType><defaultConstructorName>&lt;init&gt;</defaultConstructorName><matched>true</matched><equivalent>true</equivalent><blockInfo><blockId>0</blockId><version>modified</version><matchingBlock>0</matchingBlock><changeType>unchanged</changeType><start>13</start><end>0</end><parentBlock>-1</parentBlock></blockInfo><blockInfo><blockId>0</blockId><version>original</version><matchingBlock>0</matchingBlock><changeType>unchanged</changeType><start>13</start><end>0</end><parentBlock>-1</parentBlock></blockInfo></methodSummary><methodSummary><methodName>storeAnnotations</methodName><modModifiers>static</modModifiers><modMethodParameters>annotations</modMethodParameters><modMethodParameters>parameterAnnotations</modMethodParameters><modMethodParameters>defaultValue</modMethodParameters><modMethodParameters>optionalEnv</modMethodParameters><modMethodParamTypes>org.eclipse.jdt.internal.compiler.lookup.AnnotationBinding[]</modMethodParamTypes><modMethodParamTypes>org.eclipse.jdt.internal.compiler.lookup.AnnotationBinding[][]</modMethodParamTypes><modMethodParamTypes>java.lang.Object</modMethodParamTypes><modMethodParamTypes>org.eclipse.jdt.internal.compiler.lookup.LookupEnvironment</modMethodParamTypes><modMethodReturnType>org.eclipse.jdt.internal.compiler.lookup.AnnotationHolder</modMethodReturnType><matched>true</matched><equivalent>true</equivalent><blockInfo><blockId>0</blockId><version>modified</version><matchingBlock>0</matchingBlock><changeType>unchanged</changeType><start>17</start><end>24</end><attributes>loop</attributes><parentBlock>-1</parentBlock></blockInfo><blockInfo><blockId>1</blockId><version>modified</version><matchingBlock>1</matchingBlock><changeType>unchanged</changeType><start>18</start><end>18</end><parentBlock>0</parentBlock></blockInfo><blockInfo><blockId>2</blockId><version>modified</version><matchingBlock>2</matchingBlock><changeType>unchanged</changeType><start>19</start><end>21</end><attributes>loop</attributes><parentBlock>0</parentBlock></blockInfo><blockInfo><blockId>3</blockId><version>modified</version><matchingBlock>3</matchingBlock><changeType>unchanged</changeType><start>20</start><end>21</end><parentBlock>2</parentBlock></blockInfo><blockInfo><blockId>4</blockId><version>modified</version><matchingBlock>4</matchingBlock><changeType>unchanged</changeType><start>21</start><end>21</end><parentBlock>3</parentBlock></blockInfo><blockInfo><blockId>5</blockId><version>modified</version><matchingBlock>5</matchingBlock><changeType>unchanged</changeType><start>22</start><end>23</end><parentBlock>0</parentBlock></blockInfo><blockInfo><blockId>6</blockId><version>modified</version><matchingBlock>6</matchingBlock><changeType>unchanged</changeType><start>23</start><end>23</end><parentBlock>5</parentBlock></blockInfo><blockInfo><blockId>7</blockId><version>modified</version><matchingBlock>7</matchingBlock><changeType>unchanged</changeType><start>26</start><end>27</end><parentBlock>-1</parentBlock></blockInfo><blockInfo><blockId>8</blockId><version>modified</version><matchingBlock>8</matchingBlock><changeType>unchanged</changeType><start>27</start><end>27</end><parentBlock>7</parentBlock></blockInfo><blockInfo><blockId>9</blockId><version>modified</version><matchingBlock>9</matchingBlock><changeType>unchanged</changeType><start>28</start><end>29</end><parentBlock>-1</parentBlock></blockInfo><blockInfo><blockId>10</blockId><version>modified</version><matchingBlock>10</matchingBlock><changeType>unchanged</changeType><start>29</start><end>29</end><parentBlock>9</parentBlock></blockInfo><blockInfo><blockId>11</blockId><version>modified</version><matchingBlock>11</matchingBlock><changeType>unchanged</changeType><start>30</start><end>30</end><parentBlock>-1</parentBlock></blockInfo><blockInfo><blockId>0</blockId><version>original</version><matchingBlock>0</matchingBlock><changeType>unchanged</changeType><start>17</start><end>24</end><attributes>loop</attributes><parentBlock>-1</parentBlock></blockInfo><blockInfo><blockId>1</blockId><version>original</version><matchingBlock>1</matchingBlock><changeType>unchanged</changeType><start>18</start><end>18</end><parentBlock>0</parentBlock></blockInfo><blockInfo><blockId>2</blockId><version>original</version><matchingBlock>2</matchingBlock><changeType>unchanged</changeType><start>19</start><end>21</end><attributes>loop</attributes><parentBlock>0</parentBlock></blockInfo><blockInfo><blockId>3</blockId><version>original</version><matchingBlock>3</matchingBlock><changeType>unchanged</changeType><start>20</start><end>21</end><parentBlock>2</parentBlock></blockInfo><blockInfo><blockId>4</blockId><version>original</version><matchingBlock>4</matchingBlock><changeType>unchanged</changeType><start>21</start><end>21</end><parentBlock>3</parentBlock></blockInfo><blockInfo><blockId>5</blockId><version>original</version><matchingBlock>5</matchingBlock><changeType>unchanged</changeType><start>22</start><end>23</end><parentBlock>0</parentBlock></blockInfo><blockInfo><blockId>6</blockId><version>original</version><matchingBlock>6</matchingBlock><changeType>unchanged</changeType><start>23</start><end>23</end><parentBlock>5</parentBlock></blockInfo><blockInfo><blockId>7</blockId><version>original</version><matchingBlock>7</matchingBlock><changeType>unchanged</changeType><start>26</start><end>27</end><parentBlock>-1</parentBlock></blockInfo><blockInfo><blockId>8</blockId><version>original</version><matchingBlock>8</matchingBlock><changeType>unchanged</changeType><start>27</start><end>27</end><parentBlock>7</parentBlock></blockInfo><blockInfo><blockId>9</blockId><version>original</version><matchingBlock>9</matchingBlock><changeType>unchanged</changeType><start>28</start><end>29</end><parentBlock>-1</parentBlock></blockInfo><blockInfo><blockId>10</blockId><version>original</version><matchingBlock>10</matchingBlock><changeType>unchanged</changeType><start>29</start><end>29</end><parentBlock>9</parentBlock></blockInfo><blockInfo><blockId>11</blockId><version>original</version><matchingBlock>11</matchingBlock><changeType>unchanged</changeType><start>30</start><end>30</end><parentBlock>-1</parentBlock></blockInfo></methodSummary><methodSummary><methodName>getAnnotations</methodName><modMethodReturnType>org.eclipse.jdt.internal.compiler.lookup.AnnotationBinding[]</modMethodReturnType><matched>true</matched><equivalent>true</equivalent><blockInfo><blockId>0</blockId><version>modified</version><matchingBlock>0</matchingBlock><changeType>unchanged</changeType><start>34</start><end>34</end><parentBlock>-1</parentBlock></blockInfo><blockInfo><blockId>0</blockId><version>original</version><matchingBlock>0</matchingBlock><changeType>unchanged</changeType><start>34</start><end>34</end><parentBlock>-1</parentBlock></blockInfo></methodSummary><methodSummary><methodName>getDefaultValue</methodName><modMethodReturnType>java.lang.Object</modMethodReturnType><matched>true</matched><equivalent>true</equivalent><blockInfo><blockId>0</blockId><version>modified</version><matchingBlock>0</matchingBlock><changeType>unchanged</changeType><start>37</start><end>37</end><parentBlock>-1</parentBlock></blockInfo><blockInfo><blockId>0</blockId><version>original</version><matchingBlock>0</matchingBlock><changeType>unchanged</changeType><start>37</start><end>37</end><parentBlock>-1</parentBlock></blockInfo></methodSummary><methodSummary><methodName>getParameterAnnotations</methodName><modModifiers>public</modModifiers><modMethodReturnType>org.eclipse.jdt.internal.compiler.lookup.AnnotationBinding[][]</modMethodReturnType><matched>true</matched><equivalent>true</equivalent><blockInfo><blockId>0</blockId><version>modified</version><matchingBlock>0</matchingBlock><changeType>unchanged</changeType><start>40</start><end>40</end><parentBlock>-1</parentBlock></blockInfo><blockInfo><blockId>0</blockId><version>original</version><matchingBlock>0</matchingBlock><changeType>unchanged</changeType><start>40</start><end>40</end><parentBlock>-1</parentBlock></blockInfo></methodSummary><methodSummary><methodName>getParameterAnnotations</methodName><modMethodParameters>paramIndex</modMethodParameters><modMethodParamTypes>int</modMethodParamTypes><modMethodReturnType>org.eclipse.jdt.internal.compiler.lookup.AnnotationBinding[]</modMethodReturnType><matched>true</matched><equivalent>true</equivalent><blockInfo><blockId>0</blockId><version>modified</version><matchingBlock>0</matchingBlock><changeType>unchanged</changeType><start>43</start><end>43</end><parentBlock>-1</parentBlock></blockInfo><blockInfo><blockId>0</blockId><version>original</version><matchingBlock>0</matchingBlock><changeType>unchanged</changeType><start>43</start><end>43</end><parentBlock>-1</parentBlock></blockInfo></methodSummary><methodSummary><methodName>setAnnotations</methodName><modMethodParameters>annotations</modMethodParameters><modMethodParamTypes>org.eclipse.jdt.internal.compiler.lookup.AnnotationBinding[]</modMethodParamTypes><modMethodReturnType>org.eclipse.jdt.internal.compiler.lookup.AnnotationHolder</modMethodReturnType><matched>true</matched><equivalent>true</equivalent><blockInfo><blockId>0</blockId><version>modified</version><matchingBlock>2</matchingBlock><changeType>unchanged</changeType><start>46</start><end>46</end><parentBlock>-1</parentBlock></blockInfo><blockInfo><blockId>1</blockId><version>modified</version><matchingBlock>0</matchingBlock><changeType>unchanged</changeType><start>47</start><end>48</end><parentBlock>-1</parentBlock></blockInfo><blockInfo><blockId>2</blockId><version>modified</version><matchingBlock>1</matchingBlock><changeType>unchanged</changeType><start>48</start><end>48</end><parentBlock>1</parentBlock></blockInfo><blockInfo><blockId>3</blockId><version>modified</version><matchingBlock>3</matchingBlock><changeType>unchanged</changeType><start>49</start><end>49</end><parentBlock>-1</parentBlock></blockInfo><blockInfo><blockId>0</blockId><version>original</version><matchingBlock>1</matchingBlock><changeType>unchanged</changeType><start>46</start><end>47</end><parentBlock>-1</parentBlock></blockInfo><blockInfo><blockId>1</blockId><version>original</version><matchingBlock>2</matchingBlock><changeType>unchanged</changeType><start>47</start><end>47</end><parentBlock>0</parentBlock></blockInfo><blockInfo><blockId>2</blockId><version>original</version><matchingBlock>0</matchingBlock><changeType>unchanged</changeType><start>49</start><end>49</end><parentBlock>-1</parentBlock></blockInfo><blockInfo><blockId>3</blockId><version>original</version><matchingBlock>3</matchingBlock><changeType>unchanged</changeType><start>50</start><end>50</end><parentBlock>-1</parentBlock></blockInfo></methodSummary><classSummary><className>org.eclipse.jdt.internal.compiler.lookup.AnnotationHolder.MethodHolder</className><computeMetaData>heuristics</computeMetaData><methodSummary><methodName>MethodHolder</methodName><modMethodParameters>annotations</modMethodParameters><modMethodParameters>parameterAnnotations</modMethodParameters><modMethodParamTypes>org.eclipse.jdt.internal.compiler.lookup.AnnotationBinding[]</modMethodParamTypes><modMethodParamTypes>org.eclipse.jdt.internal.compiler.lookup.AnnotationBinding[][]</modMethodParamTypes><modMethodReturnType>void</modMethodReturnType><defaultConstructorName>&lt;init&gt;</defaultConstructorName><matched>true</matched><equivalent>true</equivalent><blockInfo><blockId>0</blockId><version>modified</version><matchingBlock>0</matchingBlock><changeType>unchanged</changeType><start>56</start><end>58</end><parentBlock>-1</parentBlock></blockInfo><blockInfo><blockId>0</blockId><version>original</version><matchingBlock>0</matchingBlock><changeType>unchanged</changeType><start>57</start><end>59</end><parentBlock>-1</parentBlock></blockInfo></methodSummary><methodSummary><methodName>getParameterAnnotations</methodName><modModifiers>public</modModifiers><modMethodReturnType>org.eclipse.jdt.internal.compiler.lookup.AnnotationBinding[][]</modMethodReturnType><matched>true</matched><equivalent>true</equivalent><blockInfo><blockId>0</blockId><version>modified</version><matchingBlock>0</matchingBlock><changeType>unchanged</changeType><start>61</start><end>61</end><parentBlock>-1</parentBlock></blockInfo><blockInfo><blockId>0</blockId><version>original</version><matchingBlock>0</matchingBlock><changeType>unchanged</changeType><start>62</start><end>62</end><parentBlock>-1</parentBlock></blockInfo></methodSummary><methodSummary><methodName>getParameterAnnotations</methodName><modMethodParameters>paramIndex</modMethodParameters><modMethodParamTypes>int</modMethodParamTypes><modMethodReturnType>org.eclipse.jdt.internal.compiler.lookup.AnnotationBinding[]</modMethodReturnType><matched>true</matched><equivalent>true</equivalent><blockInfo><blockId>0</blockId><version>modified</version><matchingBlock>0</matchingBlock><changeType>unchanged</changeType><start>64</start><end>65</end><parentBlock>-1</parentBlock></blockInfo><blockInfo><blockId>0</blockId><version>original</version><matchingBlock>0</matchingBlock><changeType>unchanged</changeType><start>65</start><end>66</end><parentBlock>-1</parentBlock></blockInfo></methodSummary><methodSummary><methodName>setAnnotations</methodName><modMethodParameters>annotations</modMethodParameters><modMethodParamTypes>org.eclipse.jdt.internal.compiler.lookup.AnnotationBinding[]</modMethodParamTypes><modMethodReturnType>org.eclipse.jdt.internal.compiler.lookup.AnnotationHolder</modMethodReturnType><matched>true</matched><equivalent>true</equivalent><blockInfo><blockId>0</blockId><version>modified</version><matchingBlock>0</matchingBlock><changeType>unchanged</changeType><start>68</start><end>69</end><parentBlock>-1</parentBlock></blockInfo><blockInfo><blockId>0</blockId><version>original</version><matchingBlock>0</matchingBlock><changeType>unchanged</changeType><start>69</start><end>70</end><parentBlock>-1</parentBlock></blockInfo></methodSummary></classSummary><classSummary><className>org.eclipse.jdt.internal.compiler.lookup.AnnotationHolder.AnnotationMethodHolder</className><computeMetaData>heuristics</computeMetaData><methodSummary><methodName>AnnotationMethodHolder</methodName><modMethodParameters>annotations</modMethodParameters><modMethodParameters>parameterAnnotations</modMethodParameters><modMethodParameters>defaultValue</modMethodParameters><modMethodParameters>optionalEnv</modMethodParameters><modMethodParamTypes>org.eclipse.jdt.internal.compiler.lookup.AnnotationBinding[]</modMethodParamTypes><modMethodParamTypes>org.eclipse.jdt.internal.compiler.lookup.AnnotationBinding[][]</modMethodParamTypes><modMethodParamTypes>java.lang.Object</modMethodParamTypes><modMethodParamTypes>org.eclipse.jdt.internal.compiler.lookup.LookupEnvironment</modMethodParamTypes><modMethodReturnType>void</modMethodReturnType><defaultConstructorName>&lt;init&gt;</defaultConstructorName><matched>true</matched><equivalent>true</equivalent><blockInfo><blockId>0</blockId><version>modified</version><matchingBlock>0</matchingBlock><changeType>unchanged</changeType><start>78</start><end>80</end><parentBlock>-1</parentBlock></blockInfo><blockInfo><blockId>0</blockId><version>original</version><matchingBlock>0</matchingBlock><changeType>unchanged</changeType><start>79</start><end>81</end><parentBlock>-1</parentBlock></blockInfo></methodSummary><methodSummary><methodName>getDefaultValue</methodName><modMethodReturnType>java.lang.Object</modMethodReturnType><matched>true</matched><equivalent>true</equivalent><blockInfo><blockId>0</blockId><version>modified</version><matchingBlock>0</matchingBlock><changeType>unchanged</changeType><start>83</start><end>87</end><parentBlock>-1</parentBlock></blockInfo><blockInfo><blockId>1</blockId><version>modified</version><matchingBlock>1</matchingBlock><changeType>unchanged</changeType><start>84</start><end>85</end><parentBlock>0</parentBlock></blockInfo><blockInfo><blockId>2</blockId><version>modified</version><matchingBlock>2</matchingBlock><changeType>unchanged</changeType><start>85</start><end>85</end><parentBlock>1</parentBlock></blockInfo><blockInfo><blockId>3</blockId><version>modified</version><matchingBlock>3</matchingBlock><changeType>unchanged</changeType><start>86</start><end>86</end><parentBlock>0</parentBlock></blockInfo><blockInfo><blockId>4</blockId><version>modified</version><matchingBlock>4</matchingBlock><changeType>unchanged</changeType><start>88</start><end>88</end><parentBlock>-1</parentBlock></blockInfo><blockInfo><blockId>0</blockId><version>original</version><matchingBlock>0</matchingBlock><changeType>unchanged</changeType><start>84</start><end>88</end><parentBlock>-1</parentBlock></blockInfo><blockInfo><blockId>1</blockId><version>original</version><matchingBlock>1</matchingBlock><changeType>unchanged</changeType><start>85</start><end>86</end><parentBlock>0</parentBlock></blockInfo><blockInfo><blockId>2</blockId><version>original</version><matchingBlock>2</matchingBlock><changeType>unchanged</changeType><start>86</start><end>86</end><parentBlock>1</parentBlock></blockInfo><blockInfo><blockId>3</blockId><version>original</version><matchingBlock>3</matchingBlock><changeType>unchanged</changeType><start>87</start><end>87</end><parentBlock>0</parentBlock></blockInfo><blockInfo><blockId>4</blockId><version>original</version><matchingBlock>4</matchingBlock><changeType>unchanged</changeType><start>89</start><end>89</end><parentBlock>-1</parentBlock></blockInfo></methodSummary></classSummary></classSummary></blockSummary>