<?xml version="1.0" encoding="UTF-8" standalone="yes"?><blockSummary><originalFile>org/eclipse/jdt/internal/formatter/FormatJavadoc.java</originalFile><modifiedFile>org/eclipse/jdt/internal/formatter/FormatJavadoc.java</modifiedFile><classSummary><className>org.eclipse.jdt.internal.formatter.FormatJavadoc</className><computeMetaData>heuristics</computeMetaData><methodSummary><methodName>FormatJavadoc</methodName><modMethodParameters>sourceStart</modMethodParameters><modMethodParameters>sourceEnd</modMethodParameters><modMethodParameters>length</modMethodParameters><modMethodParamTypes>int</modMethodParamTypes><modMethodParamTypes>int</modMethodParamTypes><modMethodParamTypes>int</modMethodParamTypes><modMethodReturnType>void</modMethodReturnType><defaultConstructorName>&lt;init&gt;</defaultConstructorName><matched>true</matched><equivalent>true</equivalent><blockInfo><blockId>0</blockId><version>modified</version><matchingBlock>0</matchingBlock><changeType>unchanged</changeType><start>30</start><end>30</end><parentBlock>-1</parentBlock></blockInfo><blockInfo><blockId>1</blockId><version>modified</version><matchingBlock>1</matchingBlock><changeType>unchanged</changeType><start>31</start><end>33</end><parentBlock>-1</parentBlock></blockInfo><blockInfo><blockId>2</blockId><version>modified</version><matchingBlock>2</matchingBlock><changeType>unchanged</changeType><start>32</start><end>32</end><parentBlock>1</parentBlock></blockInfo><blockInfo><blockId>0</blockId><version>original</version><matchingBlock>0</matchingBlock><changeType>unchanged</changeType><start>30</start><end>30</end><parentBlock>-1</parentBlock></blockInfo><blockInfo><blockId>1</blockId><version>original</version><matchingBlock>1</matchingBlock><changeType>unchanged</changeType><start>31</start><end>33</end><parentBlock>-1</parentBlock></blockInfo><blockInfo><blockId>2</blockId><version>original</version><matchingBlock>2</matchingBlock><changeType>unchanged</changeType><start>32</start><end>32</end><parentBlock>1</parentBlock></blockInfo></methodSummary><methodSummary><methodName>getFirstBlock</methodName><modModifiers>public</modModifiers><modMethodReturnType>org.eclipse.jdt.internal.formatter.FormatJavadocBlock</modMethodReturnType><matched>true</matched><equivalent>true</equivalent><blockInfo><blockId>0</blockId><version>modified</version><matchingBlock>0</matchingBlock><changeType>unchanged</changeType><start>43</start><end>45</end><parentBlock>-1</parentBlock></blockInfo><blockInfo><blockId>1</blockId><version>modified</version><matchingBlock>1</matchingBlock><changeType>unchanged</changeType><start>44</start><end>44</end><parentBlock>0</parentBlock></blockInfo><blockInfo><blockId>2</blockId><version>modified</version><matchingBlock>2</matchingBlock><changeType>unchanged</changeType><start>46</start><end>46</end><parentBlock>-1</parentBlock></blockInfo><blockInfo><blockId>0</blockId><version>original</version><matchingBlock>0</matchingBlock><changeType>unchanged</changeType><start>43</start><end>45</end><parentBlock>-1</parentBlock></blockInfo><blockInfo><blockId>1</blockId><version>original</version><matchingBlock>1</matchingBlock><changeType>unchanged</changeType><start>44</start><end>44</end><parentBlock>0</parentBlock></blockInfo><blockInfo><blockId>2</blockId><version>original</version><matchingBlock>2</matchingBlock><changeType>unchanged</changeType><start>46</start><end>46</end><parentBlock>-1</parentBlock></blockInfo></methodSummary><methodSummary><methodName>isMultiLine</methodName><modModifiers>public</modModifiers><modMethodReturnType>boolean</modMethodReturnType><matched>true</matched><equivalent>true</equivalent><blockInfo><blockId>0</blockId><version>modified</version><matchingBlock>0</matchingBlock><changeType>unchanged</changeType><start>57</start><end>57</end><parentBlock>-1</parentBlock></blockInfo><blockInfo><blockId>0</blockId><version>original</version><matchingBlock>0</matchingBlock><changeType>unchanged</changeType><start>57</start><end>57</end><parentBlock>-1</parentBlock></blockInfo></methodSummary><methodSummary><methodName>toDebugString</methodName><modModifiers>public</modModifiers><modMethodParameters>source</modMethodParameters><modMethodParamTypes>char[]</modMethodParamTypes><modMethodReturnType>java.lang.String</modMethodReturnType><matched>true</matched><equivalent>true</equivalent><blockInfo><blockId>0</blockId><version>modified</version><matchingBlock>0</matchingBlock><changeType>unchanged</changeType><start>61</start><end>63</end><parentBlock>-1</parentBlock></blockInfo><blockInfo><blockId>1</blockId><version>modified</version><matchingBlock>1</matchingBlock><changeType>unchanged</changeType><start>62</start><end>62</end><parentBlock>0</parentBlock></blockInfo><blockInfo><blockId>2</blockId><version>modified</version><matchingBlock>2</matchingBlock><changeType>unchanged</changeType><start>64</start><end>65</end><parentBlock>-1</parentBlock></blockInfo><blockInfo><blockId>3</blockId><version>modified</version><matchingBlock>3</matchingBlock><changeType>unchanged</changeType><start>66</start><end>69</end><attributes>loop</attributes><parentBlock>-1</parentBlock></blockInfo><blockInfo><blockId>4</blockId><version>modified</version><matchingBlock>4</matchingBlock><changeType>unchanged</changeType><start>67</start><end>68</end><parentBlock>3</parentBlock></blockInfo><blockInfo><blockId>5</blockId><version>modified</version><matchingBlock>5</matchingBlock><changeType>unchanged</changeType><start>70</start><end>70</end><parentBlock>-1</parentBlock></blockInfo><blockInfo><blockId>0</blockId><version>original</version><matchingBlock>0</matchingBlock><changeType>unchanged</changeType><start>61</start><end>63</end><parentBlock>-1</parentBlock></blockInfo><blockInfo><blockId>1</blockId><version>original</version><matchingBlock>1</matchingBlock><changeType>unchanged</changeType><start>62</start><end>62</end><parentBlock>0</parentBlock></blockInfo><blockInfo><blockId>2</blockId><version>original</version><matchingBlock>2</matchingBlock><changeType>unchanged</changeType><start>64</start><end>65</end><parentBlock>-1</parentBlock></blockInfo><blockInfo><blockId>3</blockId><version>original</version><matchingBlock>3</matchingBlock><changeType>unchanged</changeType><start>66</start><end>69</end><attributes>loop</attributes><parentBlock>-1</parentBlock></blockInfo><blockInfo><blockId>4</blockId><version>original</version><matchingBlock>4</matchingBlock><changeType>unchanged</changeType><start>67</start><end>68</end><parentBlock>3</parentBlock></blockInfo><blockInfo><blockId>5</blockId><version>original</version><matchingBlock>5</matchingBlock><changeType>unchanged</changeType><start>70</start><end>70</end><parentBlock>-1</parentBlock></blockInfo></methodSummary></classSummary></blockSummary>