<?xml version="1.0" encoding="UTF-8" standalone="yes"?><blockSummary><originalFile>org/eclipse/jdt/core/dom/IMethodBinding.java</originalFile><modifiedFile>org/eclipse/jdt/core/dom/IMethodBinding.java</modifiedFile><classSummary><className>org.eclipse.jdt.core.dom.IMethodBinding</className><computeMetaData>heuristics</computeMetaData><methodSummary><methodName>isConstructor</methodName><modModifiers>public</modModifiers><modModifiers>abstract</modModifiers><modMethodReturnType>boolean</modMethodReturnType><matched>true</matched><equivalent>true</equivalent></methodSummary><methodSummary><methodName>isDefaultConstructor</methodName><modModifiers>public</modModifiers><modModifiers>abstract</modModifiers><modMethodReturnType>boolean</modMethodReturnType><matched>true</matched><equivalent>true</equivalent></methodSummary><methodSummary><methodName>getName</methodName><modModifiers>public</modModifiers><modModifiers>abstract</modModifiers><modMethodReturnType>java.lang.String</modMethodReturnType><matched>true</matched><equivalent>true</equivalent></methodSummary><methodSummary><methodName>getDeclaringClass</methodName><modModifiers>public</modModifiers><modModifiers>abstract</modModifiers><modMethodReturnType>org.eclipse.jdt.core.dom.ITypeBinding</modMethodReturnType><matched>true</matched><equivalent>true</equivalent></methodSummary><methodSummary><methodName>getDefaultValue</methodName><modModifiers>public</modModifiers><modModifiers>abstract</modModifiers><modMethodReturnType>java.lang.Object</modMethodReturnType><matched>true</matched><equivalent>true</equivalent></methodSummary><methodSummary><methodName>getParameterAnnotations</methodName><modModifiers>public</modModifiers><modModifiers>abstract</modModifiers><modMethodParameters>paramIndex</modMethodParameters><modMethodParamTypes>int</modMethodParamTypes><modMethodReturnType>org.eclipse.jdt.core.dom.IAnnotationBinding[]</modMethodReturnType><matched>true</matched><equivalent>true</equivalent></methodSummary><methodSummary><methodName>getParameterTypes</methodName><modModifiers>public</modModifiers><modModifiers>abstract</modModifiers><modMethodReturnType>org.eclipse.jdt.core.dom.ITypeBinding[]</modMethodReturnType><matched>true</matched><equivalent>true</equivalent></methodSummary><methodSummary><methodName>getDeclaredReceiverType</methodName><modModifiers>public</modModifiers><modModifiers>abstract</modModifiers><modMethodReturnType>org.eclipse.jdt.core.dom.ITypeBinding</modMethodReturnType><matched>false</matched><equivalent>false</equivalent></methodSummary><methodSummary><methodName>getReturnType</methodName><modModifiers>public</modModifiers><modModifiers>abstract</modModifiers><modMethodReturnType>org.eclipse.jdt.core.dom.ITypeBinding</modMethodReturnType><matched>true</matched><equivalent>true</equivalent></methodSummary><methodSummary><methodName>getExceptionTypes</methodName><modModifiers>public</modModifiers><modModifiers>abstract</modModifiers><modMethodReturnType>org.eclipse.jdt.core.dom.ITypeBinding[]</modMethodReturnType><matched>true</matched><equivalent>true</equivalent></methodSummary><methodSummary><methodName>getTypeParameters</methodName><modModifiers>public</modModifiers><modModifiers>abstract</modModifiers><modMethodReturnType>org.eclipse.jdt.core.dom.ITypeBinding[]</modMethodReturnType><matched>true</matched><equivalent>true</equivalent></methodSummary><methodSummary><methodName>isAnnotationMember</methodName><modModifiers>public</modModifiers><modModifiers>abstract</modModifiers><modMethodReturnType>boolean</modMethodReturnType><matched>true</matched><equivalent>true</equivalent></methodSummary><methodSummary><methodName>isGenericMethod</methodName><modModifiers>public</modModifiers><modModifiers>abstract</modModifiers><modMethodReturnType>boolean</modMethodReturnType><matched>true</matched><equivalent>true</equivalent></methodSummary><methodSummary><methodName>isParameterizedMethod</methodName><modModifiers>public</modModifiers><modModifiers>abstract</modModifiers><modMethodReturnType>boolean</modMethodReturnType><matched>true</matched><equivalent>true</equivalent></methodSummary><methodSummary><methodName>getTypeArguments</methodName><modModifiers>public</modModifiers><modModifiers>abstract</modModifiers><modMethodReturnType>org.eclipse.jdt.core.dom.ITypeBinding[]</modMethodReturnType><matched>true</matched><equivalent>true</equivalent></methodSummary><methodSummary><methodName>getMethodDeclaration</methodName><modModifiers>public</modModifiers><modModifiers>abstract</modModifiers><modMethodReturnType>org.eclipse.jdt.core.dom.IMethodBinding</modMethodReturnType><matched>true</matched><equivalent>true</equivalent></methodSummary><methodSummary><methodName>isRawMethod</methodName><modModifiers>public</modModifiers><modModifiers>abstract</modModifiers><modMethodReturnType>boolean</modMethodReturnType><matched>true</matched><equivalent>true</equivalent></methodSummary><methodSummary><methodName>isSubsignature</methodName><modModifiers>public</modModifiers><modModifiers>abstract</modModifiers><modMethodParameters>otherMethod</modMethodParameters><modMethodParamTypes>org.eclipse.jdt.core.dom.IMethodBinding</modMethodParamTypes><modMethodReturnType>boolean</modMethodReturnType><matched>true</matched><equivalent>true</equivalent></methodSummary><methodSummary><methodName>isVarargs</methodName><modModifiers>public</modModifiers><modModifiers>abstract</modModifiers><modMethodReturnType>boolean</modMethodReturnType><matched>true</matched><equivalent>true</equivalent></methodSummary><methodSummary><methodName>overrides</methodName><modModifiers>public</modModifiers><modModifiers>abstract</modModifiers><modMethodParameters>method</modMethodParameters><modMethodParamTypes>org.eclipse.jdt.core.dom.IMethodBinding</modMethodParamTypes><modMethodReturnType>boolean</modMethodReturnType><matched>true</matched><equivalent>true</equivalent></methodSummary></classSummary></blockSummary>